cli/__init__.py
cli/actions.py
cli/cli.py
cli/completion.py
cli/lium_sdk.py
cli/plugin_example.py
cli/plugin_helpers.py
cli/plugins.py
cli/settings.py
cli/themed_console.py
cli/themes.json
cli/ui.py
cli/utils.py
cli/bk/__init__.py
cli/bk/logs/actions.py
cli/bk/logs/command.py
cli/bk/logs/display.py
cli/bk/logs/parsing.py
cli/bk/logs/validation.py
cli/bk/now/actions.py
cli/bk/now/command.py
cli/bk/now/parsing.py
cli/bk/now/validation.py
cli/bk/restore/actions.py
cli/bk/restore/command.py
cli/bk/restore/parsing.py
cli/bk/restore/validation.py
cli/bk/rm/actions.py
cli/bk/rm/command.py
cli/bk/rm/parsing.py
cli/bk/rm/validation.py
cli/bk/set/actions.py
cli/bk/set/command.py
cli/bk/set/parsing.py
cli/bk/set/validation.py
cli/bk/show/actions.py
cli/bk/show/command.py
cli/bk/show/parsing.py
cli/bk/show/validation.py
cli/commands/__init__.py
cli/commands/exec.py
cli/commands/mine.py
cli/config/__init__.py
cli/config/edit/actions.py
cli/config/edit/command.py
cli/config/get/actions.py
cli/config/get/command.py
cli/config/get/validation.py
cli/config/path/actions.py
cli/config/path/command.py
cli/config/reset/actions.py
cli/config/reset/command.py
cli/config/set/actions.py
cli/config/set/command.py
cli/config/set/validation.py
cli/config/show/actions.py
cli/config/show/command.py
cli/config/unset/actions.py
cli/config/unset/command.py
cli/fund/__init__.py
cli/fund/actions.py
cli/fund/command.py
cli/fund/validation.py
cli/init/__init__.py
cli/init/actions.py
cli/init/auth.py
cli/init/command.py
cli/ls/__init__.py
cli/ls/actions.py
cli/ls/command.py
cli/ls/display.py
cli/ls/validation.py
cli/ps/__init__.py
cli/ps/actions.py
cli/ps/command.py
cli/ps/display.py
cli/reboot/__init__.py
cli/reboot/actions.py
cli/reboot/command.py
cli/reboot/parsing.py
cli/reboot/validation.py
cli/rm/__init__.py
cli/rm/actions.py
cli/rm/command.py
cli/rm/display.py
cli/rm/parsing.py
cli/rm/validation.py
cli/rsync/__init__.py
cli/rsync/actions.py
cli/rsync/command.py
cli/rsync/parsing.py
lium_cli-0.6.0.dist-info/METADATA
lium_cli-0.6.0.dist-info/WHEEL
lium_cli-0.6.0.dist-info/entry_points.txt
lium_cli-0.6.0.dist-info/licenses/LICENSE
lium_cli-0.6.0.dist-info/RECORD
