Metadata-Version: 2.4
Name: lium-cli
Version: 0.6.0
Summary: A custom CLI tool for Lium. Lium CLI provides tools for interacting with the Lium ecosystem from the command line.
Project-URL: Homepage, https://github.com/Datura-ai/lium-cli
Project-URL: Repository, https://github.com/Datura-ai/lium-cli
Project-URL: Issues, https://github.com/Datura-ai/lium-cli/issues
Author-email: Lium <support@lium.io>
License-Expression: MIT
License-File: LICENSE
Classifier: Development Status :: 4 - Beta
Classifier: Intended Audience :: Developers
Classifier: Operating System :: OS Independent
Classifier: Programming Language :: Python :: 3
Classifier: Programming Language :: Python :: 3.9
Classifier: Programming Language :: Python :: 3.10
Classifier: Programming Language :: Python :: 3.11
Classifier: Programming Language :: Python :: 3.12
Requires-Python: >=3.9
Requires-Dist: aiohttp~=3.10.2
Requires-Dist: async-property==0.2.2
Requires-Dist: async-substrate-interface>=1.1.0
Requires-Dist: backoff~=2.2.1
Requires-Dist: bittensor-cli>=9.1.0
Requires-Dist: bittensor>=9.8.3
Requires-Dist: docker>=7.1.0
Requires-Dist: fuzzywuzzy~=0.18.0
Requires-Dist: gitpython>=3.0.0
Requires-Dist: jinja2
Requires-Dist: loguru>=0.7.0
Requires-Dist: netaddr~=1.3.0
Requires-Dist: paramiko>=3.5.1
Requires-Dist: plotille>=5.0.0
Requires-Dist: plotly>=6.0.0
Requires-Dist: pycryptodome<4.0.0,>=3.0.0
Requires-Dist: pydantic>=2.0.0
Requires-Dist: python-dotenv>=1.1.1
Requires-Dist: python-levenshtein
Requires-Dist: pywry>=0.6.2
Requires-Dist: pyyaml~=6.0.1
Requires-Dist: requests>=2.31.0
Requires-Dist: rich>=13.7
Requires-Dist: scalecodec==1.2.11
Requires-Dist: typer>=0.12
Provides-Extra: dev
Requires-Dist: black; extra == 'dev'
Requires-Dist: pytest; extra == 'dev'
Requires-Dist: wheel; extra == 'dev'
